LICENSE
MANIFEST.in
README.rst
requirements.txt
setup.py
data/U_kalman_datasetIII.npy
data/gliderflight_data.npy
examples/create_data_file.py
examples/my_first_example.py
examples/steady_state_example.py
gliderflight/__init__.py
gliderflight/gliderflight.py
gliderflight/glidertrim.py
gliderflight.egg-info/PKG-INFO
gliderflight.egg-info/SOURCES.txt
gliderflight.egg-info/dependency_links.txt
gliderflight.egg-info/entry_points.txt
gliderflight.egg-info/requires.txt
gliderflight.egg-info/top_level.txt
test/test.py
test/test_glidertrim.py