Metadata-Version: 2.1
Name: gliderflight
Version: 1.2.0
Summary: Flight model for Slocum ocean gliders
Home-page: https://github.com/smerckel/gliderflight
Author: Lucas Merckelbach
Author-email: lucas.merckelbach@hzg.de
License: MIT
Keywords: ocean gliders,glider flight,oceanography
Classifier: Development Status :: 4 - Beta
Classifier: Intended Audience :: Science/Research
Classifier: License :: OSI Approved :: MIT License
Classifier: Environment :: Console
Classifier: Natural Language :: English
Classifier: Operating System :: MacOS
Classifier: Operating System :: POSIX
Classifier: Programming Language :: Python :: 3.6
License-File: LICENSE
